{
  "wof:brand_name": "YMCA", 
  "wof:brand_id": 420573973, 
  "wof:categories": [
    "sg:services=social_services", 
    "sg:services=organizations", 
    "services:social_services=child_care", 
    "services:organizations=community_association", 
    "sg:entertainment=sports_and_exercise", 
    "entertainment:sports_and_exercise=gym", 
    "sg:entertainment=recreation", 
    "services:organizations=professional_association", 
    "services:organizations=nonprofit_organization", 
    "sg:services=personal", 
    "entertainment:arena=sports_club", 
    "sg:entertainment=arena", 
    "sg:entertainment=travel", 
    "entertainment:travel=campground", 
    "sg:public_place=education", 
    "public_place:education=school", 
    "services:organizations=membership_organization", 
    "sg:services=professional", 
    "entertainment:travel=hotels_and_motels", 
    "public_place:education=preschool", 
    "public_place:government=office", 
    "services:professional=employment_agencies", 
    "sg:public_place=government", 
    "entertainment:sports_and_exercise=sports_center", 
    "public_place:community_center=youth", 
    "sg:public_place=community_center", 
    "sg:retail_goods=shopping", 
    "entertainment:sports_and_exercise=playing_field", 
    "public_place:education=special_training", 
    "retail_goods:shopping=bicycles_and_sporting_goods", 
    "services:organizations=religious_organization", 
    "entertainment:sports_and_exercise=golf", 
    "entertainment:sports_and_exercise=swimming_pool", 
    "retail_goods:food_and_beverages=specialty", 
    "retail_goods:shopping=thrift_store", 
    "services:communications=radio_station", 
    "services:health_services=clinic", 
    "services:real_estate=real_estate_operator", 
    "sg:retail_goods=food_and_beverages", 
    "sg:services=communications", 
    "sg:services=health_services", 
    "sg:services=real_estate"
  ], 
  "wof:tags": [
    "organization", 
    "welfare", 
    "center", 
    "youth", 
    "health", 
    "club", 
    "community", 
    "day", 
    "gymnasium", 
    "studio", 
    "fitness", 
    "physical", 
    "program", 
    "exercise", 
    "membership", 
    "care", 
    "child", 
    "camp", 
    "social", 
    "association", 
    "cl", 
    "facility", 
    "athletic", 
    "instruction", 
    "recreational", 
    "school", 
    "charity", 
    "civic", 
    "human", 
    "organisation", 
    "trainer", 
    "voluntary", 
    "a", 
    "academic", 
    "amusement", 
    "county", 
    "elementary", 
    "family", 
    "member", 
    "placement", 
    "recreation", 
    "service/non-profit", 
    "volunteer", 
    "workers'", 
    "-", 
    "after", 
    "c", 
    "educational", 
    "gym", 
    "gymnastic", 
    "kindergarten", 
    "m", 
    "phys", 
    "physic", 
    "religious", 
    "sport", 
    "swimming", 
    "tennis", 
    "y", 
    "abuse", 
    "active", 
    "administrative", 
    "agency", 
    "amateur", 
    "apartment", 
    "as", 
    "assn", 
    "assoc", 
    "beauty", 
    "broadcasting", 
    "building", 
    "camps-recreational", 
    "christian", 
    "church", 
    "clothing", 
    "company", 
    "consultant", 
    "counselor", 
    "course", 
    "court", 
    "device", 
    "domestic", 
    "equipment", 
    "fabric", 
    "footwear", 
    "hotel", 
    "information", 
    "leisure", 
    "life", 
    "marriage", 
    "medical", 
    "military", 
    "nonprofit", 
    "nursery", 
    "operates", 
    "operation", 
    "operator", 
    "racket", 
    "secondhand", 
    "special", 
    "sporting", 
    "sports", 
    "t", 
    "team", 
    "treatment", 
    "village"
  ], 
  "wof:brand_size": "XL", 
  "wof:lastmodified": 1512416229
}