{
  "wof:brand_name": "Vans", 
  "wof:brand_id": 1125157295, 
  "wof:categories": [
    "sg:retail_goods=shopping", 
    "retail_goods:shopping=shoes", 
    "sg:services=personal", 
    "retail_goods:shopping=clothing_apparel_and_fashions", 
    "services:personal=shoe_repair_and_shine", 
    "retail_goods:shopping=bicycles_and_sporting_goods", 
    "retail_goods:shopping=department_store", 
    "services:personal=barber", 
    "services:personal=beauty_salon", 
    "services:retail=car_wash", 
    "sg:services=retail"
  ], 
  "wof:tags": [
    "store", 
    "boot", 
    "repairing", 
    "carwash", 
    "clothing", 
    "contractor", 
    "men's", 
    "shop", 
    "trade", 
    "women's"
  ], 
  "wof:brand_size": "M", 
  "wof:lastmodified": 1512416248
}