{
  "wof:brand_name": "Cargill", 
  "wof:brand_id": 1125156529, 
  "wof:categories": [
    "sg:manufacturing_and_wholesale_goods=wholesale", 
    "sg:manufacturing_and_wholesale_goods=manufacturing", 
    "manufacturing_and_wholesale_goods:wholesale=farm_supplies", 
    "manufacturing_and_wholesale_goods:manufacturing=pet_food", 
    "sg:services=professional", 
    "sg:transportation=freight", 
    "manufacturing_and_wholesale_goods:manufacturing=metals", 
    "sg:manufacturing_and_wholesale_goods=farming", 
    "manufacturing_and_wholesale_goods:wholesale=groceries", 
    "manufacturing_and_wholesale_goods:manufacturing=chemicals_and_compounds", 
    "manufacturing_and_wholesale_goods:wholesale=metals_and_minerals", 
    "sg:services=building_and_trades", 
    "manufacturing_and_wholesale_goods:farming=farm_and_veterinary_services", 
    "services:professional=business_services", 
    "services:professional=lawyer_and_legal_services", 
    "manufacturing_and_wholesale_goods:farming=crops", 
    "manufacturing_and_wholesale_goods:farming=farm", 
    "manufacturing_and_wholesale_goods:farming=livestock_farm", 
    "manufacturing_and_wholesale_goods:manufacturing=food", 
    "manufacturing_and_wholesale_goods:wholesale=chemicals_and_plastics", 
    "manufacturing_and_wholesale_goods:wholesale=meat", 
    "retail_goods:food_and_beverages=groceries_and_convenience_stores", 
    "retail_goods:shopping=pets_and_pet_supplies", 
    "services:banks_and_credit_unions=investment_brokerage", 
    "services:building_and_trades=electrical", 
    "services:building_and_trades=equipment_rental", 
    "services:building_and_trades=landscaping_services", 
    "services:organizations=community_association", 
    "services:professional=research", 
    "services:professional=testing_lab", 
    "services:utilities=natural_gas", 
    "sg:manufacturing_and_wholesale_goods=mining_and_drilling", 
    "sg:retail_goods=food_and_beverages", 
    "sg:retail_goods=shopping", 
    "sg:services=banks_and_credit_unions", 
    "sg:services=organizations", 
    "sg:services=personal", 
    "sg:services=utilities"
  ], 
  "wof:tags": [
    "mfg", 
    "feed", 
    "grain", 
    "prepared", 
    "product", 
    "center", 
    "elevator", 
    "mill", 
    "plant", 
    "farm", 
    "wire", 
    "bean", 
    "distribution", 
    "fabricated", 
    "for", 
    "salt", 
    "steel", 
    "supply", 
    "warehouse", 
    "commercial", 
    "crop", 
    "distributor", 
    "manufacturer", 
    "market", 
    "physical", 
    "preparation", 
    "advisory", 
    "almond", 
    "broker", 
    "business", 
    "canning", 
    "cattle", 
    "concentrate", 
    "contractor", 
    "cooperative", 
    "corn", 
    "cotton", 
    "establishment", 
    "feed-wholesale", 
    "field", 
    "flour", 
    "food", 
    "grocers-wholesale", 
    "grove", 
    "heat", 
    "laboratory", 
    "m", 
    "mil", 
    "milling", 
    "molasses", 
    "organizing", 
    "packing", 
    "petroleum", 
    "processing", 
    "products-wholesale", 
    "ranch", 
    "research", 
    "sales", 
    "seeding", 
    "services-household", 
    "stevedoring", 
    "storage", 
    "sugar", 
    "supplement", 
    "treating", 
    "warehousing", 
    "wet"
  ], 
  "wof:brand_size": "M", 
  "wof:lastmodified": 1512416263
}