{
  "wof:brand_name": "Ats", 
  "wof:brand_id": 420575001, 
  "wof:categories": [
    "sg:retail_goods=autos_and_motor_vehicles", 
    "retail_goods:autos_and_motor_vehicles=auto_supplies", 
    "sg:services=professional", 
    "services:retail=auto_repair", 
    "sg:services=retail", 
    "sg:manufacturing_and_wholesale_goods=wholesale", 
    "services:professional=business_services", 
    "sg:manufacturing_and_wholesale_goods=manufacturing", 
    "sg:retail_goods=shopping", 
    "sg:services=building_and_trades", 
    "manufacturing_and_wholesale_goods:wholesale=electrical", 
    "services:professional=computer_services", 
    "services:professional=management_and_consulting", 
    "sg:transportation=freight", 
    "manufacturing_and_wholesale_goods:manufacturing=printing", 
    "services:building_and_trades=electrical", 
    "manufacturing_and_wholesale_goods:manufacturing=tools_and_machinery", 
    "manufacturing_and_wholesale_goods:manufacturing=toys_and_sporting_goods", 
    "manufacturing_and_wholesale_goods:wholesale=construction_materials", 
    "manufacturing_and_wholesale_goods:wholesale=durable_goods_and_equipment", 
    "manufacturing_and_wholesale_goods:wholesale=medical_equipment_and_supplies", 
    "public_place:education=vocational_school", 
    "retail_goods:autos_and_motor_vehicles=automobile_sales", 
    "retail_goods:home_and_garden=hardware", 
    "retail_goods:shopping=clothing_apparel_and_fashions", 
    "retail_goods:shopping=pharmacy", 
    "services:building_and_trades=construction", 
    "services:building_and_trades=equipment_rental", 
    "services:health_services=dentist", 
    "services:professional=detective_and_security_services", 
    "services:professional=engineering", 
    "services:professional=testing_lab", 
    "services:utilities=sewage", 
    "sg:public_place=education", 
    "sg:retail_goods=home_and_garden", 
    "sg:services=health_services", 
    "sg:services=utilities", 
    "sg:transportation=airport", 
    "sg:transportation=local_transit", 
    "sg:transportation=transit_center", 
    "transportation:airport=general_aviation", 
    "transportation:transit_center=freight"
  ], 
  "wof:tags": [
    "tyre", 
    "establishment", 
    "car", 
    "consultant", 
    "customizing", 
    "specialist", 
    "mfg", 
    "system", 
    "alarm", 
    "computer", 
    "contractor", 
    "devices", 
    "electrical", 
    "electronic", 
    "home", 
    "manufacturer", 
    "parts", 
    "representative", 
    "training", 
    "a", 
    "accessory", 
    "acoustic", 
    "athletic", 
    "automobile", 
    "broker", 
    "brokerage", 
    "business", 
    "buy", 
    "care", 
    "coach", 
    "commercial", 
    "control", 
    "environmental", 
    "equipment", 
    "equipment-repairing", 
    "for", 
    "general", 
    "geographic", 
    "health", 
    "hydraulic", 
    "industrial", 
    "information", 
    "inspection", 
    "install", 
    "key", 
    "laboratory", 
    "legal", 
    "lock", 
    "locksmith", 
    "metal", 
    "military", 
    "motor", 
    "network", 
    "operator", 
    "performance", 
    "physician", 
    "press", 
    "refinishing", 
    "rep", 
    "repairing", 
    "security", 
    "sell", 
    "shipping", 
    "signal", 
    "solution", 
    "spare", 
    "structural", 
    "surgeon", 
    "technology", 
    "telephone", 
    "traffic", 
    "transport", 
    "trucking", 
    "typesetting", 
    "used"
  ], 
  "wof:brand_size": "L", 
  "wof:lastmodified": 1512416224
}