{
  "wof:brand_size": "M", 
  "wof:lastmodified": 1512414542, 
  "wof:tags": [
    "mfg", 
    "mill", 
    "product", 
    "foam", 
    "paperboard", 
    "box", 
    "asphalt", 
    "packaging", 
    "bag", 
    "container", 
    "fiber", 
    "for", 
    "paper", 
    "plastic", 
    "corrugated", 
    "folding", 
    "manufacturer", 
    "sales", 
    "specialty", 
    "aluminum", 
    "bags-plastic-wholesale", 
    "billing", 
    "board", 
    "bookkeeping", 
    "boxes-corrugated", 
    "converted", 
    "core", 
    "die", 
    "fe", 
    "fiber-wholesale", 
    "food", 
    "honeycomb", 
    "kraft", 
    "meat", 
    "metal", 
    "packing", 
    "poultry", 
    "protective", 
    "sanitary", 
    "satellite", 
    "shipping", 
    "solid", 
    "special", 
    "styrene", 
    "supply", 
    "tray", 
    "ult", 
    "warehouse"
  ], 
  "wof:brand_name": "Pactiv Corporation", 
  "wof:brand_id": 1125161931
}