{
  "wof:brand_size": "M", 
  "wof:lastmodified": 1512414493, 
  "wof:tags": [
    "-", 
    "business", 
    "club", 
    "night", 
    "wedding", 
    "afhaal", 
    "audio", 
    "band", 
    "bouncy", 
    "castle", 
    "child", 
    "china", 
    "clothing", 
    "cocktail", 
    "commercial", 
    "eating", 
    "glassware", 
    "hair", 
    "inflatables", 
    "lingerie", 
    "manufacturer", 
    "model", 
    "nail", 
    "nightlife", 
    "orchestra", 
    "pizza", 
    "restaurant", 
    "shop", 
    "store", 
    "supplies-wholesale", 
    "toy", 
    "underwear", 
    "verhuur", 
    "video", 
    "woman"
  ], 
  "wof:brand_name": "Fantasia", 
  "wof:brand_id": 1125159553
}