{
  "wof:brand_name": "Staples", 
  "wof:brand_id": 420574381, 
  "wof:categories": [
    "sg:retail_goods=shopping", 
    "retail_goods:shopping=stationery_and_office_supplies", 
    "sg:manufacturing_and_wholesale_goods=wholesale", 
    "sg:services=professional", 
    "services:professional=printing_and_photocopies", 
    "manufacturing_and_wholesale_goods:wholesale=computers", 
    "retail_goods:shopping=computers_and_home_electronics", 
    "manufacturing_and_wholesale_goods:wholesale=stationery", 
    "services:professional=computer_services", 
    "manufacturing_and_wholesale_goods:wholesale=office_equipment", 
    "services:building_and_trades=construction", 
    "sg:services=building_and_trades", 
    "sg:transportation=freight", 
    "services:professional=employment_agencies", 
    "sg:retail_goods=food_and_beverages", 
    "sg:services=real_estate", 
    "food_and_drink:bars_and_pubs=dive_bar", 
    "manufacturing_and_wholesale_goods:farming=livestock_farm", 
    "manufacturing_and_wholesale_goods:wholesale=furniture", 
    "manufacturing_and_wholesale_goods:wholesale=jewelry", 
    "manufacturing_and_wholesale_goods:wholesale=machinery_and_supplies", 
    "retail_goods:food_and_beverages=groceries_and_convenience_stores", 
    "retail_goods:food_and_beverages=specialty", 
    "retail_goods:home_and_garden=furniture", 
    "retail_goods:shopping=department_store", 
    "services:professional=lawyer_and_legal_services", 
    "services:professional=management_and_consulting", 
    "services:professional=secretarial_services", 
    "services:real_estate=architect", 
    "services:real_estate=real_estate_operator", 
    "services:retail=car_wash", 
    "sg:food_and_drink=bars_and_pubs", 
    "sg:manufacturing_and_wholesale_goods=farming", 
    "sg:retail_goods=home_and_garden", 
    "sg:services=retail"
  ], 
  "wof:tags": [
    "equipment", 
    "supply", 
    "furniture", 
    "software", 
    "autographic", 
    "copying", 
    "duplicating", 
    "hardware", 
    "printer", 
    "register", 
    "business", 
    "machine", 
    "com", 
    "printing", 
    "contractor", 
    "merchandise", 
    "sup", 
    "computer", 
    "photocopying", 
    "product", 
    "repair", 
    "apartment", 
    "beef", 
    "building", 
    "card", 
    "cattle", 
    "corn", 
    "designer", 
    "e", 
    "excavation", 
    "exhibit", 
    "farm", 
    "feedlot", 
    "filing", 
    "form", 
    "hanging", 
    "help", 
    "industrial", 
    "museum", 
    "other", 
    "planner", 
    "prepackaged", 
    "refrigeration", 
    "reporting", 
    "retail", 
    "shipping", 
    "special", 
    "stationary", 
    "stationery", 
    "stone", 
    "store", 
    "warehouse", 
    "whole"
  ], 
  "wof:brand_size": "XL", 
  "wof:lastmodified": 1512416237
}