{
  "wof:brand_size": "L", 
  "wof:lastmodified": 1512414444, 
  "wof:tags": [
    "bearing", 
    "industrial", 
    "equipment", 
    "power", 
    "transmission", 
    "electric", 
    "electrical", 
    "hose", 
    "hydraulic", 
    "motor", 
    "supply", 
    "fitting", 
    "parts", 
    "air conditioning", 
    "assembly", 
    "auto", 
    "automobile", 
    "consulting", 
    "coupling", 
    "cylinder", 
    "distribution", 
    "distributor", 
    "fluid", 
    "for", 
    "management", 
    "manufacturer", 
    "mfg", 
    "product", 
    "repairing", 
    "system", 
    "tool", 
    "tubing"
  ], 
  "wof:brand_name": "Motion Industries Inc", 
  "wof:brand_id": 420575451
}