{
  "wof:brand_size": "M", 
  "wof:lastmodified": 1512414540, 
  "wof:tags": [
    "shop", 
    "dealer", 
    "home", 
    "infant", 
    "wear", 
    "accessory", 
    "american", 
    "au", 
    "baby", 
    "book", 
    "bridal", 
    "ceramic", 
    "ceramics-equipment", 
    "consignment", 
    "consultant", 
    "contractor", 
    "designer", 
    "furniture", 
    "gift", 
    "hairdresser", 
    "hand", 
    "house", 
    "lingerie", 
    "maintenance", 
    "massage", 
    "mfrs", 
    "operator", 
    "pair", 
    "passenger", 
    "pastry", 
    "photographer", 
    "products-decorative", 
    "refinishing", 
    "religious", 
    "second", 
    "sleepwear", 
    "specialized", 
    "store", 
    "supply", 
    "therapist", 
    "transport", 
    "unisex", 
    "wholesaler"
  ], 
  "wof:brand_name": "Heaven Sent", 
  "wof:brand_id": 1125160853
}