{
  "wof:brand_size": "L", 
  "wof:lastmodified": 1512414459, 
  "wof:tags": [
    "exhaust", 
    "automotive", 
    "muffler", 
    "general", 
    "shop", 
    "brake", 
    "system", 
    "shock", 
    "installation", 
    "brakes", 
    "installs", 
    "absorber", 
    "repair", 
    "sales", 
    "oil", 
    "accessory", 
    "automobile", 
    "lube", 
    "tire", 
    "work", 
    "auto", 
    "car", 
    "end", 
    "front", 
    "part", 
    "parts", 
    "sale", 
    "sup", 
    "transmission", 
    "alignment", 
    "also", 
    "care", 
    "center", 
    "chang", 
    "collision", 
    "complete", 
    "full", 
    "including", 
    "install", 
    "lining", 
    "mfg", 
    "midas", 
    "motor", 
    "or", 
    "passenger", 
    "r", 
    "sp", 
    "specializing", 
    "total", 
    "vehicle"
  ], 
  "wof:brand_name": "Midas Muffler", 
  "wof:brand_id": 420574957
}