{
  "wof:brand_size": "L", 
  "wof:lastmodified": 1512414452, 
  "wof:tags": [
    "communication", 
    "radiotelephone", 
    "cellular", 
    "telephone", 
    "equipment", 
    "merchandise", 
    "data", 
    "supply", 
    "system", 
    "telecommunications-equipment", 
    "wireless", 
    "telecommunication", 
    "carrier", 
    "communications-common", 
    "messaging", 
    "paging", 
    "systems-repair", 
    "business", 
    "provider", 
    "signaling", 
    "app", 
    "auditing", 
    "boo", 
    "broadcasting", 
    "cellulars", 
    "electrical", 
    "electronic", 
    "engineering", 
    "furniture", 
    "general", 
    "internet", 
    "radio", 
    "repair", 
    "tv"
  ], 
  "wof:brand_name": "AT&T Wireless", 
  "wof:brand_id": 420575297
}