{
  "wof:brand_name": "Sovereign Bank", 
  "wof:brand_id": 1125148813, 
  "wof:categories": [
    "sg:services=banks_and_credit_unions", 
    "services:banks_and_credit_unions=bank", 
    "services:banks_and_credit_unions=financial_services"
  ], 
  "wof:tags": [
    "savings", 
    "federal", 
    "saving", 
    "commercial", 
    "loan", 
    "fed", 
    "institution", 
    "national", 
    "full", 
    "broker", 
    "association", 
    "mortgage", 
    "company", 
    "holding", 
    "real estate", 
    "state"
  ], 
  "wof:brand_size": "XL", 
  "wof:lastmodified": 1512416313
}