{
  "wof:brand_size": "M", 
  "wof:lastmodified": 1512414485, 
  "wof:tags": [
    "interior", 
    "decorator", 
    "design", 
    "consultant", 
    "decorating", 
    "designer", 
    "curtain", 
    "store", 
    "draperies", 
    "drapery", 
    "made", 
    "treatment", 
    "window", 
    "an", 
    "as", 
    "blinds-venetian", 
    "business", 
    "fixture", 
    "full", 
    "furnishers", 
    "furnishing", 
    "house", 
    "lighting", 
    "line", 
    "operates", 
    "rug", 
    "upholstery", 
    "vertical", 
    "wallcoverings", 
    "wallpaper"
  ], 
  "wof:brand_name": "Decorating Den Interiors", 
  "wof:brand_id": 1125153949
}