{
  "wof:brand_size": "XL", 
  "wof:lastmodified": 1512414454, 
  "wof:tags": [
    "yard", 
    "leasing", 
    "renting", 
    "television", 
    "radio-renting", 
    "rental", 
    "equipment", 
    "store", 
    "agency", 
    "furniture", 
    "home", 
    "rent", 
    "offer", 
    "which", 
    "appliance", 
    "own", 
    "to", 
    "electronics", 
    "electronic", 
    "operates", 
    "marketing", 
    "automobile", 
    "dryers-rental", 
    "lease", 
    "washer", 
    "contractors'", 
    "accessory", 
    "specialty", 
    "area", 
    "car", 
    "for", 
    "repair", 
    "a", 
    "as", 
    "computer", 
    "elect", 
    "furnishing", 
    "house", 
    "household", 
    "machine", 
    "maintenance", 
    "management", 
    "player", 
    "property", 
    "provides", 
    "radio", 
    "re", 
    "recorder", 
    "rent-to-own", 
    "repairing", 
    "self", 
    "supply", 
    "video", 
    "washing"
  ], 
  "wof:brand_name": "Rent-A-Center", 
  "wof:brand_id": 420573815
}