{
  "wof:brand_size": "L", 
  "wof:lastmodified": 1512414446, 
  "wof:tags": [
    "industrial", 
    "mfg", 
    "equipment", 
    "gas", 
    "welding", 
    "oxygen", 
    "helium", 
    "bulk", 
    "care", 
    "gas-industrial", 
    "home", 
    "medical-cylinder", 
    "supply", 
    "petroleum", 
    "product", 
    "apparatus", 
    "merchandise", 
    "dry", 
    "establishment", 
    "ice", 
    "repair", 
    "business", 
    "general", 
    "medical", 
    "compressor", 
    "electronic", 
    "i", 
    "local", 
    "nitrogen", 
    "organic", 
    "propane", 
    "refiner", 
    "rental", 
    "trucking", 
    "appliance", 
    "che", 
    "chem", 
    "chemical", 
    "coating", 
    "curtain", 
    "distribution", 
    "fabricated", 
    "field", 
    "h", 
    "hardware", 
    "heating", 
    "household", 
    "l", 
    "liquid", 
    "machine", 
    "machinery", 
    "nonferrous", 
    "operator", 
    "p", 
    "pa", 
    "plate", 
    "plumbing", 
    "r", 
    "refining", 
    "rent", 
    "specialty", 
    "storage", 
    "tool", 
    "transmission", 
    "wall", 
    "work"
  ], 
  "wof:brand_name": "Praxair", 
  "wof:brand_id": 420575521
}