{
  "wof:brand_name": "Glamour Shots", 
  "wof:brand_id": 1125156757, 
  "wof:categories": [
    "sg:services=retail", 
    "services:retail=portrait_studio", 
    "services:professional=art_services", 
    "sg:services=professional", 
    "sg:services=personal", 
    "services:personal=beauty_salon", 
    "services:retail=photofinishing", 
    "sg:retail_goods=shopping"
  ], 
  "wof:tags": [
    "photographer", 
    "photo", 
    "photography", 
    "store", 
    "laboratory", 
    "photographers-portrait", 
    "picture", 
    "shop", 
    "videography", 
    "wedding", 
    "commercial", 
    "photographic"
  ], 
  "wof:brand_size": "M", 
  "wof:lastmodified": 1512416250
}