{
  "wof:brand_name": "United American Insurance Co", 
  "wof:brand_id": 1125156317, 
  "wof:categories": [
    "sg:services=insurance", 
    "services:insurance=insurance_agent", 
    "services:insurance=life_insurance", 
    "services:insurance=health_insurance"
  ], 
  "wof:tags": [
    "accident", 
    "carrier", 
    "agency", 
    "carrie", 
    "health", 
    "plan", 
    "adjuster", 
    "consultant", 
    "hospitalization", 
    "surgical", 
    "underwriting"
  ], 
  "wof:brand_size": "M", 
  "wof:lastmodified": 1512416243
}