{
  "wof:brand_name": "Service Master", 
  "wof:brand_id": 1125150879, 
  "wof:categories": [
    "sg:services=building_and_trades", 
    "services:building_and_trades=cleaning_and_sanitation", 
    "services:retail=laundry_and_dry_cleaning", 
    "sg:services=retail", 
    "services:building_and_trades=construction", 
    "sg:retail_goods=home_and_garden", 
    "sg:services=professional", 
    "sg:services=social_services", 
    "manufacturing_and_wholesale_goods:wholesale=stationery", 
    "retail_goods:home_and_garden=carpets_and_floor_coverings", 
    "retail_goods:home_and_garden=household_appliances", 
    "services:building_and_trades=plumbing", 
    "services:professional=detective_and_security_services", 
    "services:social_services=adult_care", 
    "services:utilities=water", 
    "sg:manufacturing_and_wholesale_goods=wholesale", 
    "sg:services=utilities"
  ], 
  "wof:tags": [
    "carpet", 
    "rug", 
    "cleaners", 
    "restoration", 
    "damage", 
    "fire", 
    "janitor", 
    "maintenance", 
    "commercial", 
    "cleaner", 
    "contractor", 
    "emergency", 
    "house", 
    "upholstery", 
    "air", 
    "bureau", 
    "cleaning", 
    "conditioning/hvac", 
    "disaster", 
    "domestic", 
    "floor", 
    "furniture", 
    "heating", 
    "heavy", 
    "help", 
    "home", 
    "information", 
    "janitorial", 
    "on", 
    "paper", 
    "polishing", 
    "product", 
    "repair", 
    "residential", 
    "supply", 
    "water", 
    "waxing", 
    "window"
  ], 
  "wof:brand_size": "L", 
  "wof:lastmodified": 1512416239
}