{
  "wof:brand_size": "L", 
  "wof:lastmodified": 1512414479, 
  "wof:tags": [
    "shop", 
    "hairdresser", 
    "ladieswear", 
    "unisex", 
    "accessory", 
    "boutique", 
    "cards", 
    "clothing", 
    "costume", 
    "decorator", 
    "designer", 
    "establishment", 
    "gift", 
    "greeting", 
    "interior", 
    "item", 
    "mfg", 
    "specialty", 
    "ad-fulfillment", 
    "agency", 
    "antique", 
    "bathroom", 
    "beauty", 
    "bridal", 
    "building", 
    "consultant", 
    "consultants-personal", 
    "cosmetic", 
    "decor", 
    "design", 
    "equipment", 
    "fixture", 
    "formal", 
    "hair", 
    "handwoven", 
    "image", 
    "jewel", 
    "jeweler", 
    "jewelry", 
    "lady", 
    "mail", 
    "manicuring", 
    "mediterranean", 
    "men's", 
    "merchandise", 
    "order", 
    "outerwear", 
    "perfume", 
    "retail", 
    "sportswear", 
    "store", 
    "tapa", 
    "wear", 
    "wedding", 
    "women's"
  ], 
  "wof:brand_name": "Panache", 
  "wof:brand_id": 1125151513
}