{
  "wof:brand_name": "TJ Maxx", 
  "wof:brand_id": 420575947, 
  "wof:categories": [
    "sg:retail_goods=shopping", 
    "retail_goods:shopping=department_store", 
    "retail_goods:shopping=clothing_apparel_and_fashions", 
    "retail_goods:shopping=discount_and_variety_stores", 
    "sg:retail_goods=home_and_garden", 
    "retail_goods:home_and_garden=garden_supply", 
    "retail_goods:home_and_garden=home_furnishings", 
    "retail_goods:shopping=gifts_and_souvenirs", 
    "retail_goods:shopping=luggage_and_leather_goods"
  ], 
  "wof:tags": [
    "clothing", 
    "women's", 
    "apparel", 
    "discount", 
    "family", 
    "men's", 
    "accessory", 
    "children's", 
    "decor", 
    "flower", 
    "store", 
    "variety"
  ], 
  "wof:supersedes": [
    1125159105
  ], 
  "wof:brand_size": "L", 
  "wof:lastmodified": 1512416226, 
  "mz:is_current": 1
}