{
  "wof:brand_size": "M", 
  "wof:lastmodified": 1512414511, 
  "wof:tags": [
    "contractor", 
    "consultant", 
    "general", 
    "mfg", 
    "supply", 
    "automobile", 
    "car", 
    "commercial", 
    "dealer", 
    "establishment", 
    "home", 
    "janitor", 
    "mail", 
    "product", 
    "repair", 
    "repairing", 
    "accounting", 
    "advertising-promotional", 
    "air", 
    "antique", 
    "auctioneer", 
    "body", 
    "cabinet", 
    "carpentry", 
    "cat", 
    "christmas", 
    "coin", 
    "communications", 
    "conditioning", 
    "consulting", 
    "custom", 
    "delicatessen", 
    "dimension", 
    "dog", 
    "dryer", 
    "entertainer", 
    "equipment", 
    "fabricated", 
    "family", 
    "farm", 
    "flooring", 
    "foot", 
    "handyman", 
    "hardwood", 
    "help", 
    "house", 
    "kennel", 
    "landscape", 
    "laundromat", 
    "lawn", 
    "loan", 
    "machine", 
    "magician", 
    "maker", 
    "management", 
    "manufacturer", 
    "merchandise", 
    "metal", 
    "mills", 
    "miscellaneous", 
    "mobile", 
    "molding", 
    "mower", 
    "online", 
    "operated", 
    "operator", 
    "order", 
    "physician", 
    "polishing", 
    "printers'", 
    "promoter", 
    "publisher", 
    "real estate", 
    "remodeling", 
    "renovation", 
    "residential", 
    "septic", 
    "sheet", 
    "show", 
    "soybean", 
    "specialty", 
    "store", 
    "surgeon", 
    "system", 
    "tree", 
    "vending", 
    "washer", 
    "washing", 
    "wear", 
    "wire", 
    "wood", 
    "work"
  ], 
  "wof:brand_name": "M & M Enterprises", 
  "wof:brand_id": 1125157663
}