{
  "wof:brand_size": "L", 
  "wof:lastmodified": 1512414449, 
  "wof:tags": [
    "counseling", 
    "debt", 
    "credit", 
    "management", 
    "consulting", 
    "consumer", 
    "institution", 
    "organization", 
    "welfare", 
    "advisory", 
    "agency", 
    "banking", 
    "center", 
    "consultant", 
    "crane", 
    "family", 
    "finance", 
    "financial", 
    "human", 
    "individual"
  ], 
  "wof:brand_name": "Consumer Credit Counseling Svc", 
  "wof:brand_id": 420575201
}