{
  "wof:brand_size": "L", 
  "wof:lastmodified": 1512414483, 
  "wof:tags": [
    "broker", 
    "consultant", 
    "business", 
    "brokerage", 
    "coach", 
    "commodity", 
    "real estate", 
    "financial", 
    "advising", 
    "advisory", 
    "commercial", 
    "consulting", 
    "franchising", 
    "investing", 
    "merchandise", 
    "patent", 
    "property", 
    "rental", 
    "software", 
    "valuation"
  ], 
  "wof:brand_name": "Sunbelt Business Brokers", 
  "wof:brand_id": 1125152063
}