{
  "wof:brand_size": "M", 
  "wof:lastmodified": 1512414543, 
  "wof:tags": [
    "establishment", 
    "clothing", 
    "contractor", 
    "shop", 
    "ale", 
    "beer", 
    "boy", 
    "car", 
    "construction", 
    "darkroom", 
    "dealer", 
    "drinking", 
    "electrical", 
    "equipment", 
    "excavating", 
    "exporter", 
    "facility", 
    "flower", 
    "fresh", 
    "house", 
    "jewelry", 
    "line", 
    "management", 
    "operator", 
    "pawn", 
    "pension", 
    "photographers-portrait", 
    "photographic", 
    "plant", 
    "potted", 
    "rental", 
    "supply"
  ], 
  "wof:brand_name": "B & B", 
  "wof:brand_id": 1125160725
}